[{"Name":"RIVAROX","Ingredients":["rivaroksaban","ingr3","ingr44","ingr111"],"WayOfUse":"3 times a day after meal"},{"Name":"BRUFEN","Ingredients":["ibubrufen","ingr2"],"WayOfUse":"something"},{"Name":"medicine3","Ingredients":["ingr1","ing3","ingr789"],"WayOfUse":"judrfer"},{"Name":"medicine","Ingredients":["ingr1","ingr2"],"WayOfUse":"nfjksfv"},{"Name":"medicine2","Ingredients":["ingr1","ingr2","ingr3"],"WayOfUse":"3x1"},{"Name":"medicine6","Ingredients":["ingr1","ingr2"],"WayOfUse":"2x1 at 8:00 and 16:00"},{"Name":"medicine555","Ingredients":["ingr1","ingr2"],"WayOfUse":"5x1"},{"Name":"vitamin","Ingredients":["ingr1","ingr23"],"WayOfUse":"4x1"},{"Name":"medicine7777","Ingredients":["ingr1","  ingr2"," ingr3"],"WayOfUse":"3x1"}]